CHANGELOG
LICENSE
MANIFEST.in
README.md
VERSION
setup.py
shirtsio/__init__.py
shirtsio/exception.py
shirtsio/requestor.py
shirtsio/resources.py
shirtsio/version.py
shirtsio.egg-info/PKG-INFO
shirtsio.egg-info/SOURCES.txt
shirtsio.egg-info/dependency_links.txt
shirtsio.egg-info/requires.txt
shirtsio.egg-info/top_level.txt