Metadata-Version: 1.1
Name: shirtsio
Version: 1.0.0
Summary: Shirts.io API for Python
Home-page: https://github.com/ooshirts/shirtsio-python
Author: shirtsio
Author-email: support@shirts.io
License: UNKNOWN
Platform: Any
Classifier: Development Status :: 5 - Production/Stable
Classifier: Intended Audience :: Developers
Classifier: License :: OSI Approved :: MIT License
Classifier: Operating System :: OS Independent
Classifier: Programming Language :: Python
Classifier: Topic :: Software Development
Classifier: Topic :: Software Development :: Libraries
Classifier: Topic :: Software Development :: Libraries :: Python Modules
